sqlite_micromigrator/__init__.py
sqlite_micromigrator-0.2.0.dist-info/licenses/LICENSE.txt
sqlite_micromigrator-0.2.0.dist-info/METADATA
sqlite_micromigrator-0.2.0.dist-info/WHEEL
sqlite_micromigrator-0.2.0.dist-info/top_level.txt
sqlite_micromigrator-0.2.0.dist-info/RECORD
