Metadata-Version: 2.4
Name: sqlite_micromigrator
Version: 0.2.0
Summary: An SQLite migrator the tiniest and most embeddable I could make it
License: MIT License
Requires-Python: >=3.8
License-File: LICENSE.txt
Dynamic: license-file
